{
    "version": "2.16.8.11",
    "description": "WinMerge-jp",
    "homepage": "https://winmergejp.bitbucket.io/",
    "license": "GPL-2.0-only",
    "architecture": {
        "32bit": {
            "url": "https://osdn.net/dl/winmerge-jp/winmerge-2.16.8-jp-11-exe.zip",
            "hash": "4ffc23f01faaea57fe87f20fc2b9484d6287fb493b438d6c487e3dc39ea44233"
        },
        "64bit": {
            "url": "https://osdn.net/dl/winmerge-jp/winmerge-2.16.8-jp-11-x64-exe.zip",
            "hash": "788660db232029da2785571b81b6c8f207ebb93c20b109e8814b2820dfb81313"
        }
    },
    "extract_dir": "WinMerge",
    "checkver": {
        "re": "WinMerge-(?<v1>[\\d.]+)-jp-(?<v2>[\\d]+)-Setup.exe",
        "replace": "${v1}.${v2}"
    },
    "autoupdate": {
        "architecture": {
            "32bit": {
                "url": "https://osdn.net/dl/winmerge-jp/winmerge-$matchV1-jp-$matchV2-exe.zip"
            },
            "64bit": {
                "url": "https://osdn.net/dl/winmerge-jp/winmerge-$matchV1-jp-$matchV2-x64-exe.zip"
            }
        }
    },
    "bin": "WinMergeU.exe",
    "shortcuts": [
        [
            "WinMergeU.exe",
            "WinMerge"
        ]
    ]
}
